uncluster/__init__.py
uncluster/__main__.py
uncluster/synchronize.py
uncluster/uncluster.py
uncluster-0.0.1.dist-info/METADATA
uncluster-0.0.1.dist-info/WHEEL
uncluster-0.0.1.dist-info/entry_points.txt
uncluster-0.0.1.dist-info/licenses/LICENSE
uncluster-0.0.1.dist-info/RECORD
