Metadata-Version: 2.4
Name: uncluster
Version: 0.0.1
Summary: Mirror a remote folder locally via rsync.
Project-URL: Repository, https://github.com/imyizhang/uncluster
Author-email: Yi Zhang <yizhang.dev@gmail.com>
License-Expression: MIT
License-File: LICENSE
Requires-Python: >=3.12
Requires-Dist: pexpect
Requires-Dist: python-dotenv
Provides-Extra: dev
Requires-Dist: ruff; extra == 'dev'
